arachnid/__init__.py
arachnid/__main__.py
arachnid/arachnid.py
arachnid/arachnid_arg_parser.py
arachnid/arachnid_enums.py
arachnid/timewidgets.py
arachnid/crawler/__init__.py
arachnid/crawler/aopic_bank.py
arachnid/crawler/config.py
arachnid/crawler/crawler.py
arachnid/crawler/crawler_url.py
arachnid/crawler/domaindata.py
arachnid/crawler/responseparser.py
arachnid/crawler/robotparser.py
arachnid/crawler/scheduler.py
arachnid/crawler/scraper.py
arachnid/crawler/url_functions.py
arachnid/crawler/warning_issuer.py
arachnid/crawler/data/fuzz_list.txt
arachnid/crawler/data/subdomain_fuzz_list.txt
arachnid/crawler/data/warning_messages.json
arachnid_spider-0.9.5.1.dist-info/LICENSE
arachnid_spider-0.9.5.1.dist-info/METADATA
arachnid_spider-0.9.5.1.dist-info/WHEEL
arachnid_spider-0.9.5.1.dist-info/entry_points.txt
arachnid_spider-0.9.5.1.dist-info/top_level.txt
arachnid_spider-0.9.5.1.dist-info/RECORD
