Metadata-Version: 2.1
Name: arachnid-spider
Version: 0.9.5.1
Summary: An OSINT tool to find data leaks on a targeted domain
Home-page: https://github.com/jake-bickle/Arachnid
Author: Jacob Bickle, Tobin Shields
Author-email: bickle.jake@gmail.com, tobin.shields@mhcc.edu
License: GPLv3
Platform: UNKNOWN
Classifier: Programming Language :: Python :: 3
Classifier: License :: OSI Approved :: GNU General Public License v3 (GPLv3)
Classifier: Development Status :: 4 - Beta
Requires-Python: >=3.7
Requires-Dist: requests
Requires-Dist: beautifulsoup4
Requires-Dist: tldextract
Requires-Dist: pyopenssl
Requires-Dist: chardet
Requires-Dist: pyasn1
